eckitlib/__init__.py
eckitlib/bin/eckit-version
eckitlib/include/eckit/eckit.h
eckitlib/include/eckit/eckit_version.h
eckitlib/include/eckit/eckit_config.h
eckitlib/include/eckit/deprecated.h
eckitlib/include/eckit/eckit_ecbuild_config.h
eckitlib/include/eckit/cmd/DirCmd.h
eckitlib/include/eckit/cmd/RemoteCommander.h
eckitlib/include/eckit/cmd/PsCmd.h
eckitlib/include/eckit/cmd/KillCmd.h
eckitlib/include/eckit/cmd/ExportCmd.h
eckitlib/include/eckit/cmd/EchoCmd.h
eckitlib/include/eckit/cmd/LockCmd.h
eckitlib/include/eckit/cmd/UpTimeCmd.h
eckitlib/include/eckit/cmd/MemoryCmd.h
eckitlib/include/eckit/cmd/Arg.h
eckitlib/include/eckit/cmd/UserInput.h
eckitlib/include/eckit/cmd/SleepCmd.h
eckitlib/include/eckit/cmd/ConfigCmd.h
eckitlib/include/eckit/cmd/TailCmd.h
eckitlib/include/eckit/cmd/HistoryCmd.h
eckitlib/include/eckit/cmd/CmdApplication.h
eckitlib/include/eckit/cmd/LibEcKitCmd.h
eckitlib/include/eckit/cmd/StartCmd.h
eckitlib/include/eckit/cmd/ManCmd.h
eckitlib/include/eckit/cmd/CmdArg.h
eckitlib/include/eckit/cmd/RemoteCmd.h
eckitlib/include/eckit/cmd/JSONCmd.h
eckitlib/include/eckit/cmd/QuitCmd.h
eckitlib/include/eckit/cmd/RemoteCommandUser.h
eckitlib/include/eckit/cmd/TermBuf.h
eckitlib/include/eckit/cmd/AliasCmd.h
eckitlib/include/eckit/cmd/CmdParser.h
eckitlib/include/eckit/cmd/RemoteCommandable.h
eckitlib/include/eckit/cmd/StatusCmd.h
eckitlib/include/eckit/cmd/EnvironmentCmd.h
eckitlib/include/eckit/cmd/CmdResource.h
eckitlib/include/eckit/cmd/StopCmd.h
eckitlib/include/eckit/transaction/TxnLog.cc
eckitlib/include/eckit/transaction/TxnLog.h
eckitlib/include/eckit/transaction/TxnEvent.h
eckitlib/include/eckit/compat/StrStream.h
eckitlib/include/eckit/compat/Inited.h
eckitlib/include/eckit/types/Time.h
eckitlib/include/eckit/types/TimeInterval.h
eckitlib/include/eckit/types/VerifyingDate.b
eckitlib/include/eckit/types/DayOfYear.h
eckitlib/include/eckit/types/UUID.h
eckitlib/include/eckit/types/Double.b
eckitlib-1.32.3.6.dist-info/RECORD
eckitlib-1.32.3.6.dist-info/WHEEL
eckitlib-1.32.3.6.dist-info/top_level.txt
eckitlib-1.32.3.6.dist-info/METADATA
eckitlib-1.32.3.6.dist-info/licenses/LICENSE
eckitlib-1.32.3.6.dist-info/licenses/AUTHORS
