Metadata-Version: 2.4
Name: eckitlib
Version: 1.32.3.6
Summary: "eckitlib"
Author: file: AUTHORS
License-File: LICENSE
License-File: AUTHORS
Dynamic: license-file
